[
    {
        "input": "399281, Липецкая область, Хлевенский район, село Конь-Колодезь",
        "found": "Конь-Колодезь",
        "type": "locality",
        "description": "<span class=\"accuracy-tag tag-locality\">🏘️ Населенный пункт — средняя точность</span>",
        "lat": 52.154293,
        "lon": 39.138592,
        "error": "",
        "excel_row": "36",
        "route_name": "Мичуринск, Тамбовская обл."
    },
    {
        "input": "398902, Липецкая область, город Липецк, Юношеская улица, 79а",
        "found": "Юношеская, ст79а к1",
        "type": "exact",
        "description": "<span class=\"accuracy-tag tag-exact\">🏠 Здание — высокая точность</span>",
        "lat": 52.592137,
        "lon": 39.44181,
        "error": "",
        "excel_row": "38",
        "route_name": "Мичуринск, Тамбовская обл."
    },
    {
        "input": "398501, Липецкая область, Липецкий район, микрорайон Липецкий с.п Кузьмино-Отвержский сельсовет тер Комплекс Рудничный, здание 1",
        "found": "1-я, 272",
        "type": "exact",
        "description": "<span class=\"accuracy-tag tag-exact\">🏠 Здание — высокая точность</span>",
        "lat": 52.66164,
        "lon": 39.699102,
        "error": "",
        "excel_row": "39",
        "route_name": "Мичуринск, Тамбовская обл."
    },
    {
        "input": "399140, Липецкая область, Добровский район, село Доброе, Советская улица, 1А",
        "found": "Советская улица, 1а",
        "type": "exact",
        "description": "<span class=\"accuracy-tag tag-exact\">🏠 Здание — высокая точность</span>",
        "lat": 52.855138,
        "lon": 39.797996,
        "error": "",
        "excel_row": "40",
        "route_name": "Мичуринск, Тамбовская обл."
    },
    {
        "input": "393760, Тамбовская область, город Мичуринск, Гоголевская улица, 148",
        "found": "Гоголевская улица, 148",
        "type": "exact",
        "description": "<span class=\"accuracy-tag tag-exact\">🏠 Здание — высокая точность</span>",
        "lat": 52.888309,
        "lon": 40.500931,
        "error": "",
        "excel_row": "41",
        "route_name": "Мичуринск, Тамбовская обл."
    },
    {
        "input": "393760, Тамбовская область, город Мичуринск, Тамбовская улица, 108",
        "found": "Тамбовская улица, 108",
        "type": "exact",
        "description": "<span class=\"accuracy-tag tag-exact\">🏠 Здание — высокая точность</span>",
        "lat": 52.88292,
        "lon": 40.505374,
        "error": "",
        "excel_row": "42",
        "route_name": "Мичуринск, Тамбовская обл."
    },
    {
        "input": "393002, Тамбовская область, Никифоровский район, рабочий поселок Дмитриевка, улица М.Горького, 69А",
        "found": "улица Максима Горького, 69а",
        "type": "exact",
        "description": "<span class=\"accuracy-tag tag-exact\">🏠 Здание — высокая точность</span>",
        "lat": 52.894918,
        "lon": 40.785988,
        "error": "",
        "excel_row": "43",
        "route_name": "Мичуринск, Тамбовская обл."
    },
    {
        "input": "399056, Липецкая область, Грязинский район, город Грязи, улица Марата, 25",
        "found": "улица Марата, 25",
        "type": "exact",
        "description": "<span class=\"accuracy-tag tag-exact\">🏠 Здание — высокая точность</span>",
        "lat": 52.50069,
        "lon": 39.946187,
        "error": "",
        "excel_row": "44",
        "route_name": "Мичуринск, Тамбовская обл."
    },
    {
        "input": "399058, Липецкая область, Грязинский район, город Грязи, улица Воровского, 19",
        "found": "улица Воровского, 19",
        "type": "exact",
        "description": "<span class=\"accuracy-tag tag-exact\">🏠 Здание — высокая точность</span>",
        "lat": 52.494784,
        "lon": 39.948794,
        "error": "",
        "excel_row": "45",
        "route_name": "Мичуринск, Тамбовская обл."
    },
    {
        "input": "399331, Липецкая область, Усманский район, село Октябрьское, проспект Революции, 81А",
        "found": "проспект Революции, 81а",
        "type": "exact",
        "description": "<span class=\"accuracy-tag tag-exact\">🏠 Здание — высокая точность</span>",
        "lat": 52.303847,
        "lon": 39.720069,
        "error": "",
        "excel_row": "46",
        "route_name": "Мичуринск, Тамбовская обл."
    },
    {
        "input": "399370, Липецкая область, Усманский район, город Усмань, улица Радищева, 122",
        "found": "улица Радищева, 122",
        "type": "exact",
        "description": "<span class=\"accuracy-tag tag-exact\">🏠 Здание — высокая точность</span>",
        "lat": 52.053706,
        "lon": 39.73647,
        "error": "",
        "excel_row": "47",
        "route_name": "Мичуринск, Тамбовская обл."
    },
    {
        "input": "399370, Липецкая область, Усманский район, город Усмань, улица Воеводы Вельяминова, 1А",
        "found": "улица Воеводы Вельяминова, 1а",
        "type": "exact",
        "description": "<span class=\"accuracy-tag tag-exact\">🏠 Здание — высокая точность</span>",
        "lat": 52.045624,
        "lon": 39.725169,
        "error": "",
        "excel_row": "48",
        "route_name": "Мичуринск, Тамбовская обл."
    },
    {
        "input": "399370, Липецкая область, Усманский район, город Усмань, улица К.Маркса, 21",
        "found": "улица Карла Маркса, 21",
        "type": "exact",
        "description": "<span class=\"accuracy-tag tag-exact\">🏠 Здание — высокая точность</span>",
        "lat": 52.041478,
        "lon": 39.73422,
        "error": "",
        "excel_row": "50",
        "route_name": "Мичуринск, Тамбовская обл."
    }
]