[
    {
        "input": "​Автодорога Москва-Воронеж 491 километр, 2",
        "found": "автодорога Москва-Воронеж 491 километр, 2",
        "type": "exact",
        "description": "<span class=\"accuracy-tag tag-exact\">🏠 Здание — высокая точность</span>",
        "lat": 51.850005,
        "lon": 39.215599,
        "error": "",
        "excel_row": "3",
        "route_name": "Рамонский район, Воронежская обл."
    },
    {
        "input": "396002, Воронежская область, Рамонский район, село Айдарово, Промышленная зона 2 тер, 9",
        "found": "Промышленная зона, 2",
        "type": "exact",
        "description": "<span class=\"accuracy-tag tag-exact\">🏠 Здание — высокая точность</span>",
        "lat": 51.80033,
        "lon": 39.199911,
        "error": "",
        "excel_row": "4",
        "route_name": "Рамонский район, Воронежская обл."
    }
]